MANIFEST.in
README.md
setup.py
colin/__init__.py
colin-openhouse/__init__.py
colin-openhouse/version.py
colin/__pycache__/__init__.cpython-36.pyc
colin/checks/__init__.py
colin/checks/openhouse/__init__.py
colin/checks/openhouse/cmd_entrypoint.py
colin/checks/openhouse/env_var_password.py
colin/checks/openhouse/fedora_base.py
colin/checks/openhouse/file_copy.py
colin/checks/openhouse/httpd_installed.py
colin/checks/openhouse/label_maintainer.py
colin/checks/openhouse/port.py
colin/checks/openhouse/workdir.py
colin_openhouse.egg-info/PKG-INFO
colin_openhouse.egg-info/SOURCES.txt
colin_openhouse.egg-info/dependency_links.txt
colin_openhouse.egg-info/requires.txt
colin_openhouse.egg-info/top_level.txt
rulesets/openhouse.json