Metadata-Version: 1.1
Name: colin-openhouse
Version: 0.0.3
Summary: Additional chceks for colin -- the container linter. Used for image building tutorial at Open House 2018.
Home-page: https://github.com/lachmanfrantisek/colin-openhouse
Author: Frantisek Lachman
Author-email: flachman@redhat.com
License: GPLv3+
Keywords: containers,sanity,linter
Platform: UNKNOWN
Classifier: Development Status :: 4 - Beta
Classifier: Intended Audience :: Developers
Classifier: License :: OSI Approved :: GNU General Public License v2 or later (GPLv2+)
Classifier: Operating System :: POSIX :: Linux
Classifier: Programming Language :: Python :: 3
Classifier: Topic :: Software Development
Classifier: Topic :: Software Development :: Quality Assurance
Classifier: Topic :: Utilities
